sshColab/__init__.py
sshColab/code.py
ssh_Colab-0.4.17.dist-info/LICENSE
ssh_Colab-0.4.17.dist-info/METADATA
ssh_Colab-0.4.17.dist-info/WHEEL
ssh_Colab-0.4.17.dist-info/top_level.txt
ssh_Colab-0.4.17.dist-info/RECORD
