Metadata-Version: 2.1
Name: ssh-Colab
Version: 0.4.17
Summary: Google Colab secure shell connection helper that automates ngrok tunnels creation (for SSH, TPU, and TensorBoard) and facilitates the use of Google Cloud Storage, Google Drive, and Kaggle Data API.
Home-page: https://github.com/libinruan/ssh_Colab
Author: Li-Pin Juan
Author-email: lipin.juan02@gmail.com
License: UNKNOWN
Keywords: tpu,colab,ssh,tensorboard,kaggle,google drive,gcs,google cloud storage,secure shell
Platform: UNKNOWN
Classifier: Programming Language :: Python :: 3
Classifier: License :: OSI Approved :: MIT License
Classifier: Operating System :: OS Independent
Requires-Python: >=3.6
